MANIFEST.in
README.md
requirements.txt
setup.py
cairo_lang.egg-info/PKG-INFO
cairo_lang.egg-info/SOURCES.txt
cairo_lang.egg-info/dependency_links.txt
cairo_lang.egg-info/requires.txt
cairo_lang.egg-info/top_level.txt
services/__init__.py
services/config/__init__.py
services/config/general_config.py
services/everest/__init__.py
services/everest/api/__init__.py
services/everest/api/feeder_gateway/__init__.py
services/everest/api/feeder_gateway/feeder_gateway_client.py
services/everest/api/feeder_gateway/response_objects.py
services/everest/api/gateway/__init__.py
services/everest/api/gateway/gateway_client.py
services/everest/api/gateway/transaction.py
services/everest/api/gateway/transaction_type.py
services/everest/business_logic/__init__.py
services/everest/business_logic/internal_transaction.py
services/everest/business_logic/state.py
services/everest/business_logic/state_api.py
services/everest/business_logic/transaction_execution_objects.py
services/everest/definitions/__init__.py
services/everest/definitions/constants.py
services/everest/definitions/fields.py
services/everest/definitions/general_config.py
services/external_api/__init__.py
services/external_api/client.py
services/external_api/eth_gas_constants.py
services/external_api/has_uri_prefix.py
services/external_api/utils.py
starkware/__init__.py
starkware/cairo/__init__.py
starkware/cairo/bootloaders/__init__.py
starkware/cairo/bootloaders/aggregator_utils.py
starkware/cairo/bootloaders/compute_fact.py
starkware/cairo/bootloaders/fact_topology.py
starkware/cairo/bootloaders/generate_fact.py
starkware/cairo/bootloaders/hash_program.py
starkware/cairo/bootloaders/program_hash_test_utils.py
starkware/cairo/common/__init__.py
starkware/cairo/common/alloc.cairo
starkware/cairo/common/bitwise.cairo
starkware/cairo/common/bool.cairo
starkware/cairo/common/cairo_builtins.cairo
starkware/cairo/common/cairo_function_runner.py
starkware/cairo/common/copy_indices.cairo
starkware/cairo/common/default_dict.cairo
starkware/cairo/common/dict.cairo
starkware/cairo/common/dict.py
starkware/cairo/common/dict_access.cairo
starkware/cairo/common/ec.cairo
