Metadata-Version: 2.1
Name: cairo-lang
Version: 0.14.0
Summary: Compiler and runner for the Cairo language
Home-page: https://cairo-lang.org/
Author: Starkware
Author-email: info@starkware.co
Requires-Python: >=3.6
